{
    "field ": ["A14", "A15", "EX5", "EX6"],
    "description": "Ellipse semi-major axis (LM)/Ellipse semi-minor axis (Lm)",
    "bits": 5,
    "type": "byte",
    "code": [
        {"bin": "00000", "dec": 0, "param": 0.216},
        {"bin": "00001", "dec": 1, "param": 0.292},
        {"bin": "00010", "dec": 2, "param": 0.395},
        {"bin": "00011", "dec": 3, "param": 0.535},
        {"bin": "00100", "dec": 4, "param": 0.723},
        {"bin": "00101", "dec": 5, "param": 0.978},
        {"bin": "00110", "dec": 6, "param": 1.322},
        {"bin": "00111", "dec": 7, "param": 1.788},
        {"bin": "01000", "dec": 8, "param": 2.418},
        {"bin": "01001", "dec": 9, "param": 3.269},
        {"bin": "01010", "dec": 10, "param": 4.421},
        {"bin": "01011", "dec": 11, "param": 5.979},
        {"bin": "01100", "dec": 12, "param": 8.085},
        {"bin": "01101", "dec": 13, "param": 10.933},
        {"bin": "01110", "dec": 14, "param": 14.784},
        {"bin": "01111", "dec": 15, "param": 19.992},
        {"bin": "10000", "dec": 16, "param": 27.035},
        {"bin": "10001", "dec": 17, "param": 36.559},
        {"bin": "10010", "dec": 18, "param": 49.439},
        {"bin": "10011", "dec": 19, "param": 66.855},
        {"bin": "10100", "dec": 20, "param": 90.407},
        {"bin": "10101", "dec": 21, "param": 122.255},
        {"bin": "10110", "dec": 22, "param": 165.324},
        {"bin": "10111", "dec": 23, "param": 223.564},
        {"bin": "11000", "dec": 24, "param": 302.322},
        {"bin": "11001", "dec": 25, "param": 408.824},
        {"bin": "11010", "dec": 26, "param": 552.846},
        {"bin": "11011", "dec": 27, "param": 747.603},
        {"bin": "11100", "dec": 28, "param": 1010.970},
        {"bin": "11101", "dec": 29, "param": 1367.116},
        {"bin": "11110", "dec": 30, "param": 1848.727},
        {"bin": "11111", "dec": 31, "param": 2500.000}
    ]
}